{
  "page": 9,
  "results": [
    {
      "adult": false,
      "backdrop_path": "/3P52oz9HPQWxcwHOwxtyrVV1LKi.jpg",
      "genre_ids": [
        28,
        35,
        12
      ],
      "id": 383498,
      "original_language": "en",
      "original_title": "Deadpool 2",
      "overview": "Wisecracking mercenary Deadpool battles the evil and powerful Cable and other bad guys to save a boy's life.",
      "popularity": 290.738,
      "poster_path": "/to0spRl1CMDvyUbOnbb4fTk3VAd.jpg",
      "release_date": "2018-05-10",
      "title": "Deadpool 2",
      "video": false,
      "vote_average": 7.488,
      "vote_count": 16711
    },
    {
      "adult": false,
      "backdrop_path": "/6t8ES1d12OzWyCGxBeDYLHoaDrT.jpg",
      "genre_ids": [
        28,
        12,
        878
      ],
      "id": 330459,
      "original_language": "en",
      "original_title": "Rogue One: A Star Wars Story",
      "overview": "A rogue band of resistance fighters unite for a mission to steal the Death Star plans and bring a new hope to the galaxy.",
      "popularity": 34.706,
      "poster_path": "/i0yw1mFbB7sNGHCs7EXZPzFkdA1.jpg",
      "release_date": "2016-12-14",
      "title": "Rogue One: A Star Wars Story",
      "video": false,
      "vote_average": 7.488,
      "vote_count": 14644
    },
    {
      "adult": false,
      "backdrop_path": "/mabuNsGJgRuCTuGqjFkWe1xdu19.jpg",
      "genre_ids": [
        28,
        12,
        16,
        10751
      ],
      "id": 260513,
      "original_language": "en",
      "original_title": "Incredibles 2",
      "overview": "Elastigirl springs into action to save the day, while Mr. Incredible faces his greatest challenge yet – taking care of the problems of his three children.",
      "popularity": 58.786,
      "poster_path": "/9lFKBtaVIhP7E2Pk0IY1CwTKTMZ.jpg",
      "release_date": "2018-06-14",
      "title": "Incredibles 2",
      "video": false,
      "vote_average": 7.474,
      "vote_count": 12311
    },
    {
      "adult": false,
      "backdrop_path": "/pDqwUJJSaHIv2sxyRYfmYBFeU9C.jpg",
      "genre_ids": [
        18,
        35
      ],
      "id": 194662,
      "original_language": "en",
      "original_title": "Birdman or (The Unexpected Virtue of Ignorance)",
      "overview": "A fading actor best known for his portrayal of a popular superhero attempts to mount a comeback by appearing in a Broadway play. As opening night approaches, his attempts to become more altruistic, rebuild his career, and reconnect with friends and family prove more difficult than expected.",
      "popularity": 32.884,
      "poster_path": "/rHUg2AuIuLSIYMYFgavVwqt1jtc.jpg",
      "release_date": "2014-10-17",
      "title": "Birdman or (The Unexpected Virtue of Ignorance)",
      "video": false,
      "vote_average": 7.5,
      "vote_count": 12365
    },
    {
      "adult": false,
      "backdrop_path": "/ddIkmH3TpR6XSc47jj0BrGK5Rbz.jpg",
      "genre_ids": [
        10752,
        28,
        18
      ],
      "id": 374720,
      "original_language": "en",
      "original_title": "Dunkirk",
      "overview": "The story of the miraculous evacuation of Allied soldiers from Belgium, Britain, Canada and France, who were cut off and surrounded by the German army from the beaches and harbour of Dunkirk between May 26th and June 4th 1940 during World War II.",
      "popularity": 38.194,
      "poster_path": "/b4Oe15CGLL61Ped0RAS9JpqdmCt.jpg",
      "release_date": "2017-07-19",
      "title": "Dunkirk",
      "video": false,
      "vote_average": 7.456,
      "vote_count": 15808
    },
    {
      "adult": false,
      "backdrop_path": "/oVD3ClJBoomSQHtnJPAlMfes8YD.jpg",
      "genre_ids": [
        28,
        80
      ],
      "id": 339403,
      "original_language": "en",
      "original_title": "Baby Driver",
      "overview": "After being coerced into working for a crime boss, a young getaway driver finds himself taking part in a heist doomed to fail.",
      "popularity": 43.2,
      "poster_path": "/rmnQ9jKW72bHu8uKlMjPIb2VLMI.jpg",
      "release_date": "2017-06-28",
      "title": "Baby Driver",
      "video": false,
      "vote_average": 7.45,
      "vote_count": 14954
    },
    {
      "adult": false,
      "backdrop_path": "/vVpEOvdxVBP2aV166j5Xlvb5Cdc.jpg",
      "genre_ids": [
        28,
        53,
        80
      ],
      "id": 458156,
      "original_language": "en",
      "original_title": "John Wick: Chapter 3 - Parabellum",
      "overview": "Super-assassin John Wick returns with a $14 million price tag on his head and an army of bounty-hunting killers on his trail. After killing a member of the shadowy international assassin’s guild, the High Table, John Wick is excommunicado, but the world’s most ruthless hit men and women await his every turn.",
      "popularity": 76.954,
      "poster_path": "/ziEuG1essDuWuC5lpWUaw1uXY2O.jpg",
      "release_date": "2019-05-15",
      "title": "John Wick: Chapter 3 - Parabellum",
      "video": false,
      "vote_average": 7.445,
      "vote_count": 10046
    },
    {
      "adult": false,
      "backdrop_path": "/wdwcOBMkt3zmPQuEMxB3FUtMio2.jpg",
      "genre_ids": [
        12,
        28,
        878
      ],
      "id": 271110,
      "original_language": "en",
      "original_title": "Captain America: Civil War",
      "overview": "Following the events of Age of Ultron, the collective governments of the world pass an act designed to regulate all superhuman activity. This polarizes opinion amongst the Avengers, causing two factions to side with Iron Man or Captain America, which causes an epic battle between former allies.",
      "popularity": 77.541,
      "poster_path": "/rAGiXaUfPzY7CDEyNKUofk3Kw2e.jpg",
      "release_date": "2016-04-27",
      "title": "Captain America: Civil War",
      "video": false,
      "vote_average": 7.4,
      "vote_count": 21905
    },
    {
      "adult": false,
      "backdrop_path": "/oRiUKwDpcqDdoLwPoA4FIRh3hqY.jpg",
      "genre_ids": [
        35,
        18,
        53
      ],
      "id": 466272,
      "original_language": "en",
      "original_title": "Once Upon a Time… in Hollywood",
      "overview": "Los Angeles, 1969. TV star Rick Dalton, a struggling actor specializing in westerns, and stuntman Cliff Booth, his best friend, try to survive in a constantly changing movie industry. Dalton is the neighbor of the young and promising actress and model Sharon Tate, who has just married the prestigious Polish director Roman Polanski…",
      "popularity": 73.523,
      "poster_path": "/8j58iEBw9pOXFD2L0nt0ZXeHviB.jpg",
      "release_date": "2019-07-24",
      "title": "Once Upon a Time… in Hollywood",
      "video": false,
      "vote_average": 7.439,
      "vote_count": 12647
    },
    {
      "adult": false,
      "backdrop_path": "/ng6SSB3JhbcpKTwbPDsRwUYK8Cq.jpg",
      "genre_ids": [
        28,
        12,
        878
      ],
      "id": 429617,
      "original_language": "en",
      "original_title": "Spider-Man: Far From Home",
      "overview": "Peter Parker and his friends go on a summer trip to Europe. However, they will hardly be able to rest - Peter will have to agree to help Nick Fury uncover the mystery of creatures that cause natural disasters and destruction throughout the continent.",
      "popularity": 77.056,
      "poster_path": "/4q2NNj4S5dG2RLF9CpXsej7yXl.jpg",
      "release_date": "2019-06-28",
      "title": "Spider-Man: Far From Home",
      "video": false,
      "vote_average": 7.437,
      "vote_count": 14876
    },
    {
      "adult": false,
      "backdrop_path": "/boI3myFhWBvQcru4zZ15aJ0u3CX.jpg",
      "genre_ids": [
        53,
        80
      ],
      "id": 161,
      "original_language": "en",
      "original_title": "Ocean's Eleven",
      "overview": "Less than 24 hours into his parole, charismatic thief Danny Ocean is already rolling out his next plan: In one night, Danny's hand-picked crew of specialists will attempt to steal more than $150 million from three Las Vegas casinos. But to score the cash, Danny risks his chances of reconciling with ex-wife, Tess.",
      "popularity": 40.204,
      "poster_path": "/hQQCdZrsHtZyR6NbKH2YyCqd2fR.jpg",
      "release_date": "2001-12-07",
      "title": "Ocean's Eleven",
      "video": false,
      "vote_average": 7.437,
      "vote_count": 11066
    },
    {
      "adult": false,
      "backdrop_path": "/rl95VDEP3nsUQmGzE0S1S7y6T0N.jpg",
      "genre_ids": [
        10752,
        28
      ],
      "id": 190859,
      "original_language": "en",
      "original_title": "American Sniper",
      "overview": "U.S. Navy SEAL Chris Kyle takes his sole mission—protect his comrades—to heart and becomes one of the most lethal snipers in American history. His pinpoint accuracy not only saves countless lives but also makes him a prime target of insurgents. Despite grave danger and his struggle to be a good husband and father to his family back in the States, Kyle serves four tours of duty in Iraq. However, when he finally returns home, he finds that he cannot leave the war behind.",
      "popularity": 96.168,
      "poster_path": "/i1U46OwMc6vlm7OoSUKfqUH615e.jpg",
      "release_date": "2014-12-25",
      "title": "American Sniper",
      "video": false,
      "vote_average": 7.43,
      "vote_count": 12366
    },
    {
      "adult": false,
      "backdrop_path": "/oDYQhS5LtFXUP0x6bCZije5HRr9.jpg",
      "genre_ids": [
        12,
        28,
        878
      ],
      "id": 101299,
      "original_language": "en",
      "original_title": "The Hunger Games: Catching Fire",
      "overview": "Katniss Everdeen has returned home safe after winning the 74th Annual Hunger Games along with fellow tribute Peeta Mellark. Winning means that they must turn around and leave their family and close friends, embarking on a \"Victor's Tour\" of the districts. Along the way Katniss senses that a rebellion is simmering, but the Capitol is still very much in control as President Snow prepares the 75th Annual Hunger Games (The Quarter Quell) - a competition that could change Panem forever.",
      "popularity": 69.388,
      "poster_path": "/uFQbcR7h1stMlN1d3a7RmV0luLZ.jpg",
      "release_date": "2013-11-15",
      "title": "The Hunger Games: Catching Fire",
      "video": false,
      "vote_average": 7.428,
      "vote_count": 16680
    },
    {
      "adult": false,
      "backdrop_path": "/6uLhSLXzB1ooJ3522ydrBZ2Hh0W.jpg",
      "genre_ids": [
        35,
        10751
      ],
      "id": 771,
      "original_language": "en",
      "original_title": "Home Alone",
      "overview": "Eight-year-old Kevin McCallister makes the most of the situation after his family unwittingly leaves him behind when they go on Christmas vacation. But when a pair of bungling burglars set their sights on Kevin's house, the plucky kid stands ready to defend his territory. By planting booby traps galore, adorably mischievous Kevin stands his ground as his frantic mother attempts to race home before Christmas Day.",
      "popularity": 3.05,
      "poster_path": "/onTSipZ8R3bliBdKfPtsDuHTdlL.jpg",
      "release_date": "1990-11-16",
      "title": "Home Alone",
      "video": false,
      "vote_average": 7.428,
      "vote_count": 10635
    },
    {
      "adult": false,
      "backdrop_path": "/kkoiH8ZWxJ9WSAjOadGtuHUQxbm.jpg",
      "genre_ids": [
        28,
        12,
        14
      ],
      "id": 284052,
      "original_language": "en",
      "original_title": "Doctor Strange",
      "overview": "After his career is destroyed, a brilliant but arrogant surgeon gets a new lease on life when a sorcerer takes him under her wing and trains him to defend the world against evil.",
      "popularity": 54.84,
      "poster_path": "/uGBVj3bEbCoZbDjjl9wTxcygko1.jpg",
      "release_date": "2016-10-25",
      "title": "Doctor Strange",
      "video": false,
      "vote_average": 7.425,
      "vote_count": 21317
    },
    {
      "adult": false,
      "backdrop_path": "/7dzngS8pLkGJpyeskCFcjPO9qLF.jpg",
      "genre_ids": [
        28,
        53
      ],
      "id": 245891,
      "original_language": "en",
      "original_title": "John Wick",
      "overview": "Ex-hitman John Wick comes out of retirement to track down the gangsters that took everything from him.",
      "popularity": 43.097,
      "poster_path": "/fZPSd91yGE9fCcCe6OoQr6E3Bev.jpg",
      "release_date": "2014-10-22",
      "title": "John Wick",
      "video": false,
      "vote_average": 7.425,
      "vote_count": 18373
    },
    {
      "adult": false,
      "backdrop_path": "/5vDuLrjJXFS9PTF7Q1xzobmYKR9.jpg",
      "genre_ids": [
        12,
        28,
        878
      ],
      "id": 1895,
      "original_language": "en",
      "original_title": "Star Wars: Episode III - Revenge of the Sith",
      "overview": "The evil Darth Sidious enacts his final plan for unlimited power -- and the heroic Jedi Anakin Skywalker must choose a side.",
      "popularity": 41.501,
      "poster_path": "/xfSAoBEm9MNBjmlNcDYLvLSMlnq.jpg",
      "release_date": "2005-05-17",
      "title": "Star Wars: Episode III - Revenge of the Sith",
      "video": false,
      "vote_average": 7.418,
      "vote_count": 13072
    },
    {
      "adult": false,
      "backdrop_path": "/bneUTWFAcVCdsb0O5UwZbJd8xqZ.jpg",
      "genre_ids": [
        53,
        18,
        80
      ],
      "id": 1359,
      "original_language": "en",
      "original_title": "American Psycho",
      "overview": "A wealthy New York investment banking executive hides his alternate psychopathic ego from his co-workers and friends as he escalates deeper into his illogical, gratuitous fantasies.",
      "popularity": 54.039,
      "poster_path": "/9uGHEgsiUXjCNq8wdq4r49YL8A1.jpg",
      "release_date": "2000-04-13",
      "title": "American Psycho",
      "video": false,
      "vote_average": 7.4,
      "vote_count": 10211
    },
    {
      "adult": false,
      "backdrop_path": "/lcyippCCbZOliGxX7HbTNyWf98q.jpg",
      "genre_ids": [
        12,
        18
      ],
      "id": 87827,
      "original_language": "en",
      "original_title": "Life of Pi",
      "overview": "The story of an Indian boy named Pi, a zookeeper's son who finds himself in the company of a hyena, zebra, orangutan, and a Bengal tiger after a shipwreck sets them adrift in the Pacific Ocean.",
      "popularity": 41.33,
      "poster_path": "/iLgRu4hhSr6V1uManX6ukDriiSc.jpg",
      "release_date": "2012-11-20",
      "title": "Life of Pi",
      "video": false,
      "vote_average": 7.397,
      "vote_count": 12620
    },
    {
      "adult": false,
      "backdrop_path": "/roYyPiQDQKmIKUEhO912693tSja.jpg",
      "genre_ids": [
        27,
        18,
        878
      ],
      "id": 447332,
      "original_language": "en",
      "original_title": "A Quiet Place",
      "overview": "A family is forced to live in silence while hiding from creatures that hunt by sound.",
      "popularity": 109.492,
      "poster_path": "/nAU74GmpUk7t5iklEp3bufwDq4n.jpg",
      "release_date": "2018-04-03",
      "title": "A Quiet Place",
      "video": false,
      "vote_average": 7.395,
      "vote_count": 13372
    }
  ],
  "total_pages": 15,
  "total_results": 288
}